{
  "bgm": [
    "BGM_03",
    "BGM_08"
  ],
  "bgp": [
    "BG_115_A0",
    "BG_117_A0",
    "BG_189_A0"
  ],
  "egp": [],
  "cid": [
    "CHI",
    "RIN"
  ],
  "label": [
    {
      "name": "SCR_L_YC_ARRV_A3_START",
      "line": 0
    },
    {
      "name": "SCR_L_YC_ARRV_A3_GP1",
      "line": 5
    },
    {
      "name": "SCR_L_YC_ARRV_A3_GP2",
      "line": 60
    },
    {
      "name": "SCR_L_YC_ARRV_A3_GP3",
      "line": 131
    },
    {
      "name": "SCR_L_YC_ARRV_A3_ALLEND",
      "line": 194
    }
  ],
  "message": [
    {
      "function": "XAUTOSAVE_SCENE",
      "argument": [],
      "name": "",
      "msgidx": -1,
      "voice": "",
      "vid": "",
      "value": "",
      "said": ""
    },
    {
      "function": "XCLR",
      "argument": [],
      "name": "",
      "msgidx": -1,
      "voice": "",
      "vid": "",
      "value": "",
      "said": ""
    },
    {
      "function": "XAGBRANCH",
      "argument": [
        "1",
        "SCR_L_YC_ARRV_A3_GP1"
      ],
      "name": "",
      "msgidx": -1,
      "voice": "",
      "vid": "",
      "value": "",
      "said": ""
    },
    {
      "function": "XAGBRANCH",
      "argument": [
        "2",
        "SCR_L_YC_ARRV_A3_GP2"
      ],
      "name": "",
      "msgidx": -1,
      "voice": "",
      "vid": "",
      "value": "",
      "said": ""
    },
    {
      "function": "XAGBRANCH",
      "argument": [
        "3",
        "SCR_L_YC_ARRV_A3_GP3"
      ],
      "name": "",
      "msgidx": -1,
      "voice": "",
      "vid": "",
      "value": "",
      "said": ""
    },
    {
      "function": "XCLR",
      "argument": [],
      "name": "",
      "msgidx": -1,
      "voice": "",
      "vid": "",
      "value": "",
      "said": ""
    },
    {
      "function": "XFADE",
      "argument": [
        "XFTS,MaskTexture.None,0",
        "XFOT,0.5"
      ],
      "name": "",
      "msgidx": -1,
      "voice": "",
      "vid": "",
      "value": "",
      "said": ""
    },
    {
      "function": "XWXB",
      "argument": [],
      "name": "",
      "msgidx": -1,
      "voice": "",
      "vid": "",
      "value": "",
      "said": ""
    },
    {
      "function": "SNSE",
      "argument": [
        "NSE_OFF",
        "0"
      ],
      "name": "",
      "msgidx": -1,
      "voice": "",
      "vid": "",
      "value": "",
      "said": ""
    },
    {
      "function": "XWXB",
      "argument": [],
      "name": "",
      "msgidx": -1,
      "voice": "",
      "vid": "",
      "value": "",
      "said": ""
    },
    {
      "function": "XLCYDRAW",
      "argument": [
        "XLCYLOAD,Lucy.Type.BACK,BG_117_A0",
        "XLCYFADE,0,0.001"
      ],
      "name": "",
      "msgidx": -1,
      "voice": "",
      "vid": "",
      "value": "",
      "said": ""
    },
    {
      "function": "XLCYDRAW",
      "argument": [
        "XLCYINIT",
        "XLCYFIND,FindType.SP_C",
        "XLCYLOAD,Lucy.Type.BUST,BU_OFF",
        "XLCYLOAD,Lucy.Type.SP_L,SP_OFF",
        "XLCYLOAD,Lucy.Type.SP_R,SP_OFF",
        "XLCYLOAD,Lucy.Type.SP_C,SP_OFF",
        "XLCYLOAD,Lucy.Type.MG_0,MG_OFF",
        "XLCYLOAD,Lucy.Type.MG_1,MG_OFF",
        "XLCYFADE,0,0.25"
      ],
      "name": "",
      "msgidx": -1,
      "voice": "",
      "vid": "",
      "value": "",
      "said": ""
    },
    {
      "function": "SBGM",
      "argument": [
        "BGM_03"
      ],
      "name": "",
      "msgidx": -1,
      "voice": "",
      "vid": "",
      "value": "",
      "said": ""
    },
    {
      "function": "SESE",
      "argument": [
        "ESE_OFF",
        "0"
      ],
      "name": "",
      "msgidx": -1,
      "voice": "",
      "vid": "",
      "value": "",
      "said": ""
    },
    {
      "function": "XMON",
      "argument": [],
      "name": "",
      "msgidx": -1,
      "voice": "",
      "vid": "",
      "value": "",
      "said": ""
    },
    {
      "function": "XFADE",
      "argument": [
        "XFTS,MaskTexture.None,0",
        "XFIN,0.5"
      ],
      "name": "",
      "msgidx": -1,
      "voice": "",
      "vid": "",
      "value": "",
      "said": ""
    },
    {
      "function": "XCUTINSET",
      "argument": [
        "L1",
        "1",
        "NAD_SML",
        "1",
        "-1",
        "-1",
        "NONE",
        "T_OFF",
        "A_NON",
        "CutinActive.V_ON"
      ],
      "name": "",
      "msgidx": -1,
      "voice": "",
      "vid": "",
      "value": "",
      "said": ""
    },
    {
      "function": "XCUTINDRAW",
      "argument": [],
      "name": "",
      "msgidx": -1,
      "voice": "",
      "vid": "",
      "value": "",
      "said": ""
    },
    {
      "function": "XMESS",
      "argument": [
        "Oh, isn't the entrance over there, Takabotchi",
        "Plateau written?"
      ],
      "name": "Nadeshiko",
      "msgidx": 0,
      "voice": "NAD_0430_0001",
      "vid": "VID_NAD",
      "value": "",
      "said": ""
    },
    {
      "function": "XWCR",
      "argument": [],
      "name": "",
      "msgidx": -1,
      "voice": "",
      "vid": "",
      "value": "",
      "said": ""
    },
    {
      "function": "XCUTINSET",
      "argument": [
        "R2",
        "0",
        "RIN_NML",
        "3",
        "-1",
        "-1",
        "NONE",
        "T_OFF",
        "A_NON",
        "CutinActive.V_ON"
      ],
      "name": "",
      "msgidx": -1,
      "voice": "",
      "vid": "",
      "value": "",
      "said": ""
    },
    {
      "function": "XCUTINDRAW",
      "argument": [],
      "name": "",
      "msgidx": -1,
      "voice": "",
      "vid": "",
      "value": "",
      "said": ""
    },
    {
      "function": "XMESS",
      "argument": [
        "Oh, it's written."
      ],
      "name": "Rin",
      "msgidx": 1,
      "voice": "RIN_0157_0002",
      "vid": "VID_RIN",
      "value": "",
      "said": ""
    },
    {
      "function": "XWCR",
      "argument": [],
      "name": "",
      "msgidx": -1,
      "voice": "",
      "vid": "",
      "value": "",
      "said": ""
    },
    {
      "function": "XCUTINSET",
      "argument": [
        "L1",
        "1",
        "NAD_SML",
        "1",
        "-1",
        "-1",
        "NONE",
        "T_OFF",
        "A_NON",
        "CutinActive.V_ON"
      ],
      "name": "",
      "msgidx": -1,
      "voice": "",
      "vid": "",
      "value": "",
      "said": ""
    },
    {
      "function": "XCUTINDRAW",
      "argument": [],
      "name": "",
      "msgidx": -1,
      "voice": "",
      "vid": "",
      "value": "",
      "said": ""
    },
    {
      "function": "XMESS",
      "argument": [
        "That means ..."
      ],
      "name": "Nadeshiko",
      "msgidx": 2,
      "voice": "NAD_0431_0003",
      "vid": "VID_NAD",
      "value": "",
      "said": ""
    },
    {
      "function": "XWCR",
      "argument": [],
      "name": "",
      "msgidx": -1,
      "voice": "",
      "vid": "",
      "value": "",
      "said": ""
    },
    {
      "function": "XCUTINSET",
      "argument": [
        "R2",
        "0",
        "RIN_SML",
        "3",
        "-1",
        "-1",
        "NONE",
        "T_OFF",
        "A_NON",
        "CutinActive.V_ON"
      ],
      "name": "",
      "msgidx": -1,
      "voice": "",
      "vid": "",
      "value": "",
      "said": ""
    },
    {
      "function": "XCUTINDRAW",
      "argument": [],
      "name": "",
      "msgidx": -1,
      "voice": "",
      "vid": "",
      "value": "",
      "said": ""
    },
    {
      "function": "XMESS",
      "argument": [
        "good work. Arrived at Takabotchi Plateau."
      ],
      "name": "Rin",
      "msgidx": 3,
      "voice": "RIN_0158_0004",
      "vid": "VID_RIN",
      "value": "",
      "said": ""
    },
    {
      "function": "XWCR",
      "argument": [],
      "name": "",
      "msgidx": -1,
      "voice": "",
      "vid": "",
      "value": "",
      "said": ""
    },
    {
      "function": "XCUTINSET",
      "argument": [
        "L1",
        "1",
        "NAD_HPY",
        "1",
        "-1",
        "-1",
        "NONE",
        "T_OFF",
        "A_NON",
        "CutinActive.V_ON"
      ],
      "name": "",
      "msgidx": -1,
      "voice": "",
      "vid": "",
      "value": "",
      "said": ""
    },
    {
      "function": "XCUTINDRAW",
      "argument": [],
      "name": "",
      "msgidx": -1,
      "voice": "",
      "vid": "",
      "value": "",
      "said": ""
    },
    {
      "function": "XMESS",
      "argument": [
        "Hooray!"
      ],
      "name": "Nadeshiko",
      "msgidx": 4,
      "voice": "NAD_0432_0005",
      "vid": "VID_NAD",
      "value": "",
      "said": ""
    },
    {
      "function": "XWCR",
      "argument": [],
      "name": "",
      "msgidx": -1,
      "voice": "",
      "vid": "",
      "value": "",
      "said": ""
    },
    {
      "function": "SBGM",
      "argument": [
        "BGM_OFF"
      ],
      "name": "",
      "msgidx": -1,
      "voice": "",
      "vid": "",
      "value": "",
      "said": ""
    },
    {
      "function": "XCUTINCLEAR",
      "argument": [
        "4"
      ],
      "name": "",
      "msgidx": -1,
      "voice": "",
      "vid": "",
      "value": "",
      "said": ""
    },
    {
      "function": "XPLACEENTRY",
      "argument": [
        "3"
      ],
      "name": "",
      "msgidx": -1,
      "voice": "",
      "vid": "",
      "value": "",
      "said": ""
    },
    {
      "function": "XFADE",
      "argument": [
        "XFTS,MaskTexture.None,0",
        "XFOT,0.5"
      ],
      "name": "",
      "msgidx": -1,
      "voice": "",
      "vid": "",
      "value": "",
      "said": ""
    },
    {
      "function": "XWXB",
      "argument": [],
      "name": "",
      "msgidx": -1,
      "voice": "",
      "vid": "",
      "value": "",
      "said": ""
    },
    {
      "function": "SNSE",
      "argument": [
        "NSE_OFF",
        "0"
      ],
      "name": "",
      "msgidx": -1,
      "voice": "",
      "vid": "",
      "value": "",
      "said": ""
    },
    {
      "function": "XWXB",
      "argument": [],
      "name": "",
      "msgidx": -1,
      "voice": "",
      "vid": "",
      "value": "",
      "said": ""
    },
    {
      "function": "XLCYDRAW",
      "argument": [
        "XLCYLOAD,Lucy.Type.BACK,BG_189_A0",
        "XLCYFADE,0,0.001"
      ],
      "name": "",
      "msgidx": -1,
      "voice": "",
      "vid": "",
      "value": "",
      "said": ""
    },
    {
      "function": "XLCYDRAW",
      "argument": [
        "XLCYINIT",
        "XLCYFIND,FindType.SP_C",
        "XLCYLOAD,Lucy.Type.BUST,BU_OFF",
        "XLCYLOAD,Lucy.Type.SP_L,SP_OFF",
        "XLCYLOAD,Lucy.Type.SP_R,SP_OFF",
        "XLCYLOAD,Lucy.Type.SP_C,SP_OFF",
        "XLCYLOAD,Lucy.Type.MG_0,MG_OFF",
        "XLCYLOAD,Lucy.Type.MG_1,MG_OFF",
        "XLCYFADE,0,0.25"
      ],
      "name": "",
      "msgidx": -1,
      "voice": "",
      "vid": "",
      "value": "",
      "said": ""
    },
    {
      "function": "SBGM",
      "argument": [
        "BGM_08"
      ],
      "name": "",
      "msgidx": -1,
      "voice": "",
      "vid": "",
      "value": "",
      "said": ""
    },
    {
      "function": "SESE",
      "argument": [
        "ESE_OFF",
        "0"
      ],
      "name": "",
      "msgidx": -1,
      "voice": "",
      "vid": "",
      "value": "",
      "said": ""
    },
    {
      "function": "XMON",
      "argument": [],
      "name": "",
      "msgidx": -1,
      "voice": "",
      "vid": "",
      "value": "",
      "said": ""
    },
    {
      "function": "XFADE",
      "argument": [
        "XFTS,MaskTexture.None,0",
        "XFIN,0.5"
      ],
      "name": "",
      "msgidx": -1,
      "voice": "",
      "vid": "",
      "value": "",
      "said": ""
    },
    {
      "function": "XMESS",
      "argument": [
        "Sakura-san, thank you for driving so far."
      ],
      "name": "Rin",
      "msgidx": 5,
      "voice": "RIN_0159_0006",
      "vid": "VID_RIN",
      "value": "",
      "said": ""
    },
    {
      "function": "XWCR",
      "argument": [],
      "name": "",
      "msgidx": -1,
      "voice": "",
      "vid": "",
      "value": "",
      "said": ""
    },
    {
      "function": "XMESS",
      "argument": [
        "you're welcome. I'm glad I got it safely."
      ],
      "name": "Sakura",
      "msgidx": 6,
      "voice": "SAK_0120_0007",
      "vid": "VID_SAK",
      "value": "",
      "said": ""
    },
    {
      "function": "XWCR",
      "argument": [],
      "name": "",
      "msgidx": -1,
      "voice": "",
      "vid": "",
      "value": "",
      "said": ""
    },
    {
      "function": "XMESS",
      "argument": [
        "But it seems that there is still a distance",
        "to the vicinity of the mountaintop."
      ],
      "name": "Sakura",
      "msgidx": 7,
      "voice": "SAK_0121_0008",
      "vid": "VID_SAK",
      "value": "",
      "said": ""
    },
    {
      "function": "XWCR",
      "argument": [],
      "name": "",
      "msgidx": -1,
      "voice": "",
      "vid": "",
      "value": "",
      "said": ""
    },
    {
      "function": "XMESS",
      "argument": [
        "(Preparing for the camp ...)"
      ],
      "name": "Rin（thinking）",
      "msgidx": 8,
      "voice": "",
      "vid": "",
      "value": "",
      "said": ""
    },
    {
      "function": "XWCR",
      "argument": [],
      "name": "",
      "msgidx": -1,
      "voice": "",
      "vid": "",
      "value": "",
      "said": ""
    },
    {
      "function": "XMESS",
      "argument": [
        "(Can I still do it later)"
      ],
      "name": "Rin（thinking）",
      "msgidx": 9,
      "voice": "",
      "vid": "",
      "value": "",
      "said": ""
    },
    {
      "function": "XWCR",
      "argument": [],
      "name": "",
      "msgidx": -1,
      "voice": "",
      "vid": "",
      "value": "",
      "said": ""
    },
    {
      "function": "GON",
      "argument": [
        "SCR_L_YC_ARRV_A3_ALLEND"
      ],
      "name": "",
      "msgidx": -1,
      "voice": "",
      "vid": "",
      "value": "",
      "said": ""
    },
    {
      "function": "XCLR",
      "argument": [],
      "name": "",
      "msgidx": -1,
      "voice": "",
      "vid": "",
      "value": "",
      "said": ""
    },
    {
      "function": "XFADE",
      "argument": [
        "XFTS,MaskTexture.None,0",
        "XFOT,0.5"
      ],
      "name": "",
      "msgidx": -1,
      "voice": "",
      "vid": "",
      "value": "",
      "said": ""
    },
    {
      "function": "XWXB",
      "argument": [],
      "name": "",
      "msgidx": -1,
      "voice": "",
      "vid": "",
      "value": "",
      "said": ""
    },
    {
      "function": "SNSE",
      "argument": [
        "NSE_OFF",
        "0"
      ],
      "name": "",
      "msgidx": -1,
      "voice": "",
      "vid": "",
      "value": "",
      "said": ""
    },
    {
      "function": "XWXB",
      "argument": [],
      "name": "",
      "msgidx": -1,
      "voice": "",
      "vid": "",
      "value": "",
      "said": ""
    },
    {
      "function": "XLCYDRAW",
      "argument": [
        "XLCYLOAD,Lucy.Type.BACK,BG_117_A0",
        "XLCYFADE,0,0.001"
      ],
      "name": "",
      "msgidx": -1,
      "voice": "",
      "vid": "",
      "value": "",
      "said": ""
    },
    {
      "function": "XLCYDRAW",
      "argument": [
        "XLCYINIT",
        "XLCYFIND,FindType.SP_C",
        "XLCYLOAD,Lucy.Type.BUST,BU_OFF",
        "XLCYLOAD,Lucy.Type.SP_L,SP_OFF",
        "XLCYLOAD,Lucy.Type.SP_R,SP_OFF",
        "XLCYLOAD,Lucy.Type.SP_C,SP_OFF",
        "XLCYLOAD,Lucy.Type.MG_0,MG_OFF",
        "XLCYLOAD,Lucy.Type.MG_1,MG_OFF",
        "XLCYFADE,0,0.25"
      ],
      "name": "",
      "msgidx": -1,
      "voice": "",
      "vid": "",
      "value": "",
      "said": ""
    },
    {
      "function": "SBGM",
      "argument": [
        "BGM_03"
      ],
      "name": "",
      "msgidx": -1,
      "voice": "",
      "vid": "",
      "value": "",
      "said": ""
    },
    {
      "function": "SESE",
      "argument": [
        "ESE_OFF",
        "0"
      ],
      "name": "",
      "msgidx": -1,
      "voice": "",
      "vid": "",
      "value": "",
      "said": ""
    },
    {
      "function": "XMON",
      "argument": [],
      "name": "",
      "msgidx": -1,
      "voice": "",
      "vid": "",
      "value": "",
      "said": ""
    },
    {
      "function": "XFADE",
      "argument": [
        "XFTS,MaskTexture.None,0",
        "XFIN,0.5"
      ],
      "name": "",
      "msgidx": -1,
      "voice": "",
      "vid": "",
      "value": "",
      "said": ""
    },
    {
      "function": "XCUTINSET",
      "argument": [
        "L1",
        "2",
        "CHI_HPY",
        "1",
        "0",
        "-1",
        "NONE",
        "T_OFF",
        "A_NON",
        "CutinActive.V_ON"
      ],
      "name": "",
      "msgidx": -1,
      "voice": "",
      "vid": "",
      "value": "",
      "said": ""
    },
    {
      "function": "XCUTINDRAW",
      "argument": [],
      "name": "",
      "msgidx": -1,
      "voice": "",
      "vid": "",
      "value": "",
      "said": ""
    },
    {
      "function": "XMESS",
      "argument": [
        "I did it, Inuko!"
      ],
      "name": "Chiaki",
      "msgidx": 10,
      "voice": "CHI_0265_0009",
      "vid": "VID_CHI",
      "value": "",
      "said": ""
    },
    {
      "function": "XWCR",
      "argument": [],
      "name": "",
      "msgidx": -1,
      "voice": "",
      "vid": "",
      "value": "",
      "said": ""
    },
    {
      "function": "XCUTINSET",
      "argument": [
        "L2",
        "3",
        "AOI_HPY",
        "1",
        "-1",
        "AOI_HPY",
        "NONE",
        "T_OFF",
        "A_NON",
        "CutinActive.V_ON"
      ],
      "name": "",
      "msgidx": -1,
      "voice": "",
      "vid": "",
      "value": "",
      "said": ""
    },
    {
      "function": "XCUTINDRAW",
      "argument": [],
      "name": "",
      "msgidx": -1,
      "voice": "",
      "vid": "",
      "value": "",
      "said": ""
    },
    {
      "function": "XMESS",
      "argument": [
        "Oh, I did it. I finally arrived."
      ],
      "name": "Aoi",
      "msgidx": 11,
      "voice": "AOI_0261_0010",
      "vid": "VID_AOI",
      "value": "",
      "said": ""
    },
    {
      "function": "XWCR",
      "argument": [],
      "name": "",
      "msgidx": -1,
      "voice": "",
      "vid": "",
      "value": "",
      "said": ""
    },
    {
      "function": "XCUTINSET",
      "argument": [
        "L1",
        "2",
        "CHI_HPY",
        "1",
        "0",
        "-1",
        "NONE",
        "T_OFF",
        "A_NON",
        "CutinActive.V_ON"
      ],
      "name": "",
      "msgidx": -1,
      "voice": "",
      "vid": "",
      "value": "",
      "said": ""
    },
    {
      "function": "XCUTINSET",
      "argument": [
        "L2",
        "3",
        "AOI_HPY",
        "1",
        "-1",
        "AOI_HPY",
        "NONE",
        "T_OFF",
        "A_NON",
        "CutinActive.V_ON"
      ],
      "name": "",
      "msgidx": -1,
      "voice": "",
      "vid": "",
      "value": "",
      "said": ""
    },
    {
      "function": "XCUTINDRAW",
      "argument": [],
      "name": "",
      "msgidx": -1,
      "voice": "",
      "vid": "",
      "value": "",
      "said": ""
    },
    {
      "function": "XMESS",
      "argument": [
        "To Takabotchi Plateau!"
      ],
      "name": "Chiaki and Aoi",
      "msgidx": 12,
      "voice": "CHI_0266_0011",
      "vid": "VID_CHI",
      "value": "",
      "said": ""
    },
    {
      "function": "XWCR",
      "argument": [],
      "name": "",
      "msgidx": -1,
      "voice": "",
      "vid": "",
      "value": "",
      "said": ""
    },
    {
      "function": "SBGM",
      "argument": [
        "BGM_OFF"
      ],
      "name": "",
      "msgidx": -1,
      "voice": "",
      "vid": "",
      "value": "",
      "said": ""
    },
    {
      "function": "XCUTINCLEAR",
      "argument": [
        "4"
      ],
      "name": "",
      "msgidx": -1,
      "voice": "",
      "vid": "",
      "value": "",
      "said": ""
    },
    {
      "function": "XPLACEENTRY",
      "argument": [
        "3"
      ],
      "name": "",
      "msgidx": -1,
      "voice": "",
      "vid": "",
      "value": "",
      "said": ""
    },
    {
      "function": "XFADE",
      "argument": [
        "XFTS,MaskTexture.None,0",
        "XFOT,0.5"
      ],
      "name": "",
      "msgidx": -1,
      "voice": "",
      "vid": "",
      "value": "",
      "said": ""
    },
    {
      "function": "XWXB",
      "argument": [],
      "name": "",
      "msgidx": -1,
      "voice": "",
      "vid": "",
      "value": "",
      "said": ""
    },
    {
      "function": "SNSE",
      "argument": [
        "NSE_OFF",
        "0"
      ],
      "name": "",
      "msgidx": -1,
      "voice": "",
      "vid": "",
      "value": "",
      "said": ""
    },
    {
      "function": "XWXB",
      "argument": [],
      "name": "",
      "msgidx": -1,
      "voice": "",
      "vid": "",
      "value": "",
      "said": ""
    },
    {
      "function": "XLCYDRAW",
      "argument": [
        "XLCYLOAD,Lucy.Type.BACK,BG_189_A0",
        "XLCYFADE,0,0.001"
      ],
      "name": "",
      "msgidx": -1,
      "voice": "",
      "vid": "",
      "value": "",
      "said": ""
    },
    {
      "function": "XLCYDRAW",
      "argument": [
        "XLCYINIT",
        "XLCYFIND,FindType.SP_C",
        "XLCYLOAD,Lucy.Type.BUST,BU_OFF",
        "XLCYLOAD,Lucy.Type.SP_L,SP_OFF",
        "XLCYLOAD,Lucy.Type.SP_R,SP_OFF",
        "XLCYLOAD,Lucy.Type.SP_C,SP_OFF",
        "XLCYLOAD,Lucy.Type.MG_0,MG_OFF",
        "XLCYLOAD,Lucy.Type.MG_1,MG_OFF",
        "XLCYFADE,0,0.25"
      ],
      "name": "",
      "msgidx": -1,
      "voice": "",
      "vid": "",
      "value": "",
      "said": ""
    },
    {
      "function": "SBGM",
      "argument": [
        "BGM_08"
      ],
      "name": "",
      "msgidx": -1,
      "voice": "",
      "vid": "",
      "value": "",
      "said": ""
    },
    {
      "function": "SESE",
      "argument": [
        "ESE_OFF",
        "0"
      ],
      "name": "",
      "msgidx": -1,
      "voice": "",
      "vid": "",
      "value": "",
      "said": ""
    },
    {
      "function": "XMON",
      "argument": [],
      "name": "",
      "msgidx": -1,
      "voice": "",
      "vid": "",
      "value": "",
      "said": ""
    },
    {
      "function": "XFADE",
      "argument": [
        "XFTS,MaskTexture.None,0",
        "XFIN,0.5"
      ],
      "name": "",
      "msgidx": -1,
      "voice": "",
      "vid": "",
      "value": "",
      "said": ""
    },
    {
      "function": "XMESS",
      "argument": [
        "(From the previous place, I climbed a",
        "mountain road quite a bit)"
      ],
      "name": "Rin（thinking）",
      "msgidx": 13,
      "voice": "",
      "vid": "",
      "value": "",
      "said": ""
    },
    {
      "function": "XWCR",
      "argument": [],
      "name": "",
      "msgidx": -1,
      "voice": "",
      "vid": "",
      "value": "",
      "said": ""
    },
    {
      "function": "XMESS",
      "argument": [
        "Hey, Rin-chan. Which area do you think is",
        "best for camping?"
      ],
      "name": "Nadeshiko",
      "msgidx": 14,
      "voice": "NAD_0433_0012",
      "vid": "VID_NAD",
      "value": "",
      "said": ""
    },
    {
      "function": "XWCR",
      "argument": [],
      "name": "",
      "msgidx": -1,
      "voice": "",
      "vid": "",
      "value": "",
      "said": ""
    },
    {
      "function": "XMESS",
      "argument": [
        "What do you think of Professor Toba?"
      ],
      "name": "Rin",
      "msgidx": 15,
      "voice": "RIN_0160_0013",
      "vid": "VID_RIN",
      "value": "",
      "said": ""
    },
    {
      "function": "XWCR",
      "argument": [],
      "name": "",
      "msgidx": -1,
      "voice": "",
      "vid": "",
      "value": "",
      "said": ""
    },
    {
      "function": "XMESS",
      "argument": [
        "Well, for me ..."
      ],
      "name": "Toba-sensei",
      "msgidx": 16,
      "voice": "MIN_0177_0014",
      "vid": "VID_MIN",
      "value": "",
      "said": ""
    },
    {
      "function": "XWCR",
      "argument": [],
      "name": "",
      "msgidx": -1,
      "voice": "",
      "vid": "",
      "value": "",
      "said": ""
    },
    {
      "function": "XFADE",
      "argument": [
        "XFTS,MaskTexture.None,0",
        "XFOT,0.5"
      ],
      "name": "",
      "msgidx": -1,
      "voice": "",
      "vid": "",
      "value": "",
      "said": ""
    },
    {
      "function": "XWXB",
      "argument": [],
      "name": "",
      "msgidx": -1,
      "voice": "",
      "vid": "",
      "value": "",
      "said": ""
    },
    {
      "function": "SNSE",
      "argument": [
        "NSE_OFF",
        "0"
      ],
      "name": "",
      "msgidx": -1,
      "voice": "",
      "vid": "",
      "value": "",
      "said": ""
    },
    {
      "function": "XWXB",
      "argument": [],
      "name": "",
      "msgidx": -1,
      "voice": "",
      "vid": "",
      "value": "",
      "said": ""
    },
    {
      "function": "XLCYDRAW",
      "argument": [
        "XLCYLOAD,Lucy.Type.BACK,BG_115_A0",
        "XLCYFADE,0,0.001"
      ],
      "name": "",
      "msgidx": -1,
      "voice": "",
      "vid": "",
      "value": "",
      "said": ""
    },
    {
      "function": "XLCYDRAW",
      "argument": [
        "XLCYINIT",
        "XLCYFIND,FindType.SP_C",
        "XLCYLOAD,Lucy.Type.BUST,BU_OFF",
        "XLCYLOAD,Lucy.Type.SP_L,SP_OFF",
        "XLCYLOAD,Lucy.Type.SP_R,SP_OFF",
        "XLCYLOAD,Lucy.Type.SP_C,SP_OFF",
        "XLCYLOAD,Lucy.Type.MG_0,MG_OFF",
        "XLCYLOAD,Lucy.Type.MG_1,MG_OFF",
        "XLCYFADE,0,0.25"
      ],
      "name": "",
      "msgidx": -1,
      "voice": "",
      "vid": "",
      "value": "",
      "said": ""
    },
    {
      "function": "SBGM",
      "argument": [
        "BGM_SAME"
      ],
      "name": "",
      "msgidx": -1,
      "voice": "",
      "vid": "",
      "value": "",
      "said": ""
    },
    {
      "function": "SESE",
      "argument": [
        "ESE_OFF",
        "0"
      ],
      "name": "",
      "msgidx": -1,
      "voice": "",
      "vid": "",
      "value": "",
      "said": ""
    },
    {
      "function": "XMON",
      "argument": [],
      "name": "",
      "msgidx": -1,
      "voice": "",
      "vid": "",
      "value": "",
      "said": ""
    },
    {
      "function": "XFADE",
      "argument": [
        "XFTS,MaskTexture.None,0",
        "XFIN,0.5"
      ],
      "name": "",
      "msgidx": -1,
      "voice": "",
      "vid": "",
      "value": "",
      "said": ""
    },
    {
      "function": "XCUTINSET",
      "argument": [
        "R1",
        "5",
        "MIN_NML",
        "2",
        "0",
        "-1",
        "NONE",
        "T_OFF",
        "A_NON",
        "CutinActive.V_ON"
      ],
      "name": "",
      "msgidx": -1,
      "voice": "",
      "vid": "",
      "value": "",
      "said": ""
    },
    {
      "function": "XCUTINDRAW",
      "argument": [],
      "name": "",
      "msgidx": -1,
      "voice": "",
      "vid": "",
      "value": "",
      "said": ""
    },
    {
      "function": "XMESS",
      "argument": [
        "Is it around here?"
      ],
      "name": "Toba-sensei",
      "msgidx": 17,
      "voice": "MIN_0178_0015",
      "vid": "VID_MIN",
      "value": "",
      "said": ""
    },
    {
      "function": "XWCR",
      "argument": [],
      "name": "",
      "msgidx": -1,
      "voice": "",
      "vid": "",
      "value": "",
      "said": ""
    },
    {
      "function": "SNSE",
      "argument": [
        "NSE_102",
        "0"
      ],
      "name": "",
      "msgidx": -1,
      "voice": "",
      "vid": "",
      "value": "",
      "said": ""
    },
    {
      "function": "XWTM",
      "argument": [
        "0.066"
      ],
      "name": "",
      "msgidx": -1,
      "voice": "",
      "vid": "",
      "value": "",
      "said": ""
    },
    {
      "function": "XWXB",
      "argument": [],
      "name": "",
      "msgidx": -1,
      "voice": "",
      "vid": "",
      "value": "",
      "said": ""
    },
    {
      "function": "XLCYDRAW",
      "argument": [
        "XLCYFIND,FindType.SP_C",
        "XLCYLOAD,Lucy.Type.BUST,BU_CHI_CMM4_0_LAU",
        "XLCYLOAD,Lucy.Type.SP_L,SP_OFF",
        "XLCYLOAD,Lucy.Type.SP_R,SP_OFF",
        "XLCYLOAD,Lucy.Type.SP_C,SP_OFF",
        "XLCYFADE,0,0.25"
      ],
      "name": "",
      "msgidx": -1,
      "voice": "",
      "vid": "",
      "value": "",
      "said": ""
    },
    {
      "function": "XMESS",
      "argument": [
        "Alright! From now on, we will be our main",
        "team! Everyone, get ready to set up!"
      ],
      "name": "Chiaki",
      "msgidx": 18,
      "voice": "CHI_0267_0016",
      "vid": "VID_CHI",
      "value": "",
      "said": ""
    },
    {
      "function": "XWCR",
      "argument": [],
      "name": "",
      "msgidx": -1,
      "voice": "",
      "vid": "",
      "value": "",
      "said": ""
    },
    {
      "function": "XCUTINSET",
      "argument": [
        "L1",
        "1",
        "NAD_SML",
        "1",
        "-1",
        "-1",
        "NONE",
        "T_OFF",
        "A_NON",
        "CutinActive.V_ON"
      ],
      "name": "",
      "msgidx": -1,
      "voice": "",
      "vid": "",
      "value": "",
      "said": ""
    },
    {
      "function": "XCUTINSET",
      "argument": [
        "L2",
        "3",
        "AOI_SML",
        "1",
        "-1",
        "AOI_SML",
        "NONE",
        "T_OFF",
        "A_NON",
        "CutinActive.V_ON"
      ],
      "name": "",
      "msgidx": -1,
      "voice": "",
      "vid": "",
      "value": "",
      "said": ""
    },
    {
      "function": "XCUTINDRAW",
      "argument": [],
      "name": "",
      "msgidx": -1,
      "voice": "",
      "vid": "",
      "value": "",
      "said": ""
    },
    {
      "function": "XMESS",
      "argument": [
        "Oh!"
      ],
      "name": "The Outclub (Nadeshiko and Aoi)",
      "msgidx": 19,
      "voice": "NAD_0434_0017",
      "vid": "VID_NAD",
      "value": "",
      "said": ""
    },
    {
      "function": "XWCR",
      "argument": [],
      "name": "",
      "msgidx": -1,
      "voice": "",
      "vid": "",
      "value": "",
      "said": ""
    },
    {
      "function": "GON",
      "argument": [
        "SCR_L_YC_ARRV_A3_ALLEND"
      ],
      "name": "",
      "msgidx": -1,
      "voice": "",
      "vid": "",
      "value": "",
      "said": ""
    },
    {
      "function": "XCLR",
      "argument": [],
      "name": "",
      "msgidx": -1,
      "voice": "",
      "vid": "",
      "value": "",
      "said": ""
    },
    {
      "function": "XFADE",
      "argument": [
        "XFTS,MaskTexture.None,0",
        "XFOT,0.5"
      ],
      "name": "",
      "msgidx": -1,
      "voice": "",
      "vid": "",
      "value": "",
      "said": ""
    },
    {
      "function": "XWXB",
      "argument": [],
      "name": "",
      "msgidx": -1,
      "voice": "",
      "vid": "",
      "value": "",
      "said": ""
    },
    {
      "function": "SNSE",
      "argument": [
        "NSE_OFF",
        "0"
      ],
      "name": "",
      "msgidx": -1,
      "voice": "",
      "vid": "",
      "value": "",
      "said": ""
    },
    {
      "function": "XWXB",
      "argument": [],
      "name": "",
      "msgidx": -1,
      "voice": "",
      "vid": "",
      "value": "",
      "said": ""
    },
    {
      "function": "XLCYDRAW",
      "argument": [
        "XLCYLOAD,Lucy.Type.BACK,BG_117_A0",
        "XLCYFADE,0,0.001"
      ],
      "name": "",
      "msgidx": -1,
      "voice": "",
      "vid": "",
      "value": "",
      "said": ""
    },
    {
      "function": "XLCYDRAW",
      "argument": [
        "XLCYINIT",
        "XLCYFIND,FindType.SP_C",
        "XLCYLOAD,Lucy.Type.BUST,BU_OFF",
        "XLCYLOAD,Lucy.Type.SP_L,SP_OFF",
        "XLCYLOAD,Lucy.Type.SP_R,SP_OFF",
        "XLCYLOAD,Lucy.Type.SP_C,SP_OFF",
        "XLCYLOAD,Lucy.Type.MG_0,MG_OFF",
        "XLCYLOAD,Lucy.Type.MG_1,MG_OFF",
        "XLCYFADE,0,0.25"
      ],
      "name": "",
      "msgidx": -1,
      "voice": "",
      "vid": "",
      "value": "",
      "said": ""
    },
    {
      "function": "SBGM",
      "argument": [
        "BGM_03"
      ],
      "name": "",
      "msgidx": -1,
      "voice": "",
      "vid": "",
      "value": "",
      "said": ""
    },
    {
      "function": "SESE",
      "argument": [
        "ESE_OFF",
        "0"
      ],
      "name": "",
      "msgidx": -1,
      "voice": "",
      "vid": "",
      "value": "",
      "said": ""
    },
    {
      "function": "XMON",
      "argument": [],
      "name": "",
      "msgidx": -1,
      "voice": "",
      "vid": "",
      "value": "",
      "said": ""
    },
    {
      "function": "XFADE",
      "argument": [
        "XFTS,MaskTexture.None,0",
        "XFIN,0.5"
      ],
      "name": "",
      "msgidx": -1,
      "voice": "",
      "vid": "",
      "value": "",
      "said": ""
    },
    {
      "function": "XMESS",
      "argument": [
        "(Taka ... Takabotchi ...)"
      ],
      "name": "Rin（thinking）",
      "msgidx": 20,
      "voice": "",
      "vid": "",
      "value": "",
      "said": ""
    },
    {
      "function": "XWCR",
      "argument": [],
      "name": "",
      "msgidx": -1,
      "voice": "",
      "vid": "",
      "value": "",
      "said": ""
    },
    {
      "function": "XCUTINSET",
      "argument": [
        "L1",
        "0",
        "RIN_EXC",
        "5",
        "-1",
        "-1",
        "NONE",
        "T_OFF",
        "A_NON",
        "CutinActive.V_ON"
      ],
      "name": "",
      "msgidx": -1,
      "voice": "",
      "vid": "",
      "value": "",
      "said": ""
    },
    {
      "function": "XCUTINDRAW",
      "argument": [],
      "name": "",
      "msgidx": -1,
      "voice": "",
      "vid": "",
      "value": "",
      "said": ""
    },
    {
      "function": "XMESS",
      "argument": [
        "I'm finally here ..."
      ],
      "name": "Rin",
      "msgidx": 21,
      "voice": "RIN_0161_0018",
      "vid": "VID_RIN",
      "value": "",
      "said": ""
    },
    {
      "function": "XWCR",
      "argument": [],
      "name": "",
      "msgidx": -1,
      "voice": "",
      "vid": "",
      "value": "",
      "said": ""
    },
    {
      "function": "XCUTINCLEAR",
      "argument": [
        "4"
      ],
      "name": "",
      "msgidx": -1,
      "voice": "",
      "vid": "",
      "value": "",
      "said": ""
    },
    {
      "function": "XMESS",
      "argument": [
        "(A superb view spot known to those in the",
        "know)"
      ],
      "name": "Rin（thinking）",
      "msgidx": 22,
      "voice": "",
      "vid": "",
      "value": "",
      "said": ""
    },
    {
      "function": "XWCR",
      "argument": [],
      "name": "",
      "msgidx": -1,
      "voice": "",
      "vid": "",
      "value": "",
      "said": ""
    },
    {
      "function": "XMESS",
      "argument": [
        "(Takabotchi plateau!)"
      ],
      "name": "Rin（thinking）",
      "msgidx": 23,
      "voice": "",
      "vid": "",
      "value": "",
      "said": ""
    },
    {
      "function": "XWCR",
      "argument": [],
      "name": "",
      "msgidx": -1,
      "voice": "",
      "vid": "",
      "value": "",
      "said": ""
    },
    {
      "function": "XMESS",
      "argument": [
        "(From the top, you can see Matsumoto City,",
        "Lake Suwa, and even Mt. Fuji)"
      ],
      "name": "Rin（thinking）",
      "msgidx": 24,
      "voice": "",
      "vid": "",
      "value": "",
      "said": ""
    },
    {
      "function": "XWCR",
      "argument": [],
      "name": "",
      "msgidx": -1,
      "voice": "",
      "vid": "",
      "value": "",
      "said": ""
    },
    {
      "function": "XMESS",
      "argument": [
        "(9km to the top!)"
      ],
      "name": "Rin（thinking）",
      "msgidx": 25,
      "voice": "",
      "vid": "",
      "value": "",
      "said": ""
    },
    {
      "function": "XWCR",
      "argument": [],
      "name": "",
      "msgidx": -1,
      "voice": "",
      "vid": "",
      "value": "",
      "said": ""
    },
    {
      "function": "XIF",
      "argument": [
        "0",
        "C_CAMP",
        "C_EQU",
        "7",
        "C_END"
      ],
      "name": "",
      "msgidx": -1,
      "voice": "",
      "vid": "",
      "value": "",
      "said": ""
    },
    {
      "function": "XFADE",
      "argument": [
        "XFTS,MaskTexture.None,0",
        "XFOT,0.5"
      ],
      "name": "",
      "msgidx": -1,
      "voice": "",
      "vid": "",
      "value": "",
      "said": ""
    },
    {
      "function": "XWXB",
      "argument": [],
      "name": "",
      "msgidx": -1,
      "voice": "",
      "vid": "",
      "value": "",
      "said": ""
    },
    {
      "function": "SNSE",
      "argument": [
        "NSE_OFF",
        "0"
      ],
      "name": "",
      "msgidx": -1,
      "voice": "",
      "vid": "",
      "value": "",
      "said": ""
    },
    {
      "function": "XWXB",
      "argument": [],
      "name": "",
      "msgidx": -1,
      "voice": "",
      "vid": "",
      "value": "",
      "said": ""
    },
    {
      "function": "XLCYDRAW",
      "argument": [
        "XLCYLOAD,Lucy.Type.BACK,BG_115_A0",
        "XLCYFADE,0,0.001"
      ],
      "name": "",
      "msgidx": -1,
      "voice": "",
      "vid": "",
      "value": "",
      "said": ""
    },
    {
      "function": "XLCYDRAW",
      "argument": [
        "XLCYFIND,FindType.SP_C",
        "XLCYLOAD,Lucy.Type.BUST,BU_OFF",
        "XLCYLOAD,Lucy.Type.SP_L,SP_OFF",
        "XLCYLOAD,Lucy.Type.SP_R,SP_OFF",
        "XLCYLOAD,Lucy.Type.SP_C,SP_RIN_CMM6_2_BCK",
        "XLCYFADE,0,0.25"
      ],
      "name": "",
      "msgidx": -1,
      "voice": "",
      "vid": "",
      "value": "",
      "said": ""
    },
    {
      "function": "SBGM",
      "argument": [
        "BGM_SAME"
      ],
      "name": "",
      "msgidx": -1,
      "voice": "",
      "vid": "",
      "value": "",
      "said": ""
    },
    {
      "function": "SESE",
      "argument": [
        "ESE_OFF",
        "0"
      ],
      "name": "",
      "msgidx": -1,
      "voice": "",
      "vid": "",
      "value": "",
      "said": ""
    },
    {
      "function": "XMON",
      "argument": [],
      "name": "",
      "msgidx": -1,
      "voice": "",
      "vid": "",
      "value": "",
      "said": ""
    },
    {
      "function": "XFADE",
      "argument": [
        "XFTS,MaskTexture.None,0",
        "XFIN,0.5"
      ],
      "name": "",
      "msgidx": -1,
      "voice": "",
      "vid": "",
      "value": "",
      "said": ""
    },
    {
      "function": "XMESS",
      "argument": [
        "arrived……."
      ],
      "name": "Rin",
      "msgidx": 26,
      "voice": "RIN_0162_0019",
      "vid": "VID_RIN",
      "value": "",
      "said": ""
    },
    {
      "function": "XWCR",
      "argument": [],
      "name": "",
      "msgidx": -1,
      "voice": "",
      "vid": "",
      "value": "",
      "said": ""
    },
    {
      "function": "XLCYDRAW",
      "argument": [
        "XLCYLOAD,Lucy.Type.BUST,BU_OFF",
        "XLCYLOAD,Lucy.Type.AUTO,SP_RIN_CMM6_2_BCK",
        "XLCYFADE,0,0.25"
      ],
      "name": "",
      "msgidx": -1,
      "voice": "",
      "vid": "",
      "value": "",
      "said": ""
    },
    {
      "function": "XMESS",
      "argument": [
        "(150km, I ran all the way!)"
      ],
      "name": "Rin（thinking）",
      "msgidx": 27,
      "voice": "",
      "vid": "",
      "value": "",
      "said": ""
    },
    {
      "function": "XWCR",
      "argument": [],
      "name": "",
      "msgidx": -1,
      "voice": "",
      "vid": "",
      "value": "",
      "said": ""
    },
    {
      "function": "XLCYDRAW",
      "argument": [
        "XLCYLOAD,Lucy.Type.BUST,BU_OFF",
        "XLCYLOAD,Lucy.Type.AUTO,SP_RIN_CMM6_2_BCK",
        "XLCYFADE,0,0.25"
      ],
      "name": "",
      "msgidx": -1,
      "voice": "",
      "vid": "",
      "value": "",
      "said": ""
    },
    {
      "function": "XMESS",
      "argument": [
        "Huh ……."
      ],
      "name": "Rin",
      "msgidx": 28,
      "voice": "RIN_0163_0020",
      "vid": "VID_RIN",
      "value": "",
      "said": ""
    },
    {
      "function": "XWCR",
      "argument": [],
      "name": "",
      "msgidx": -1,
      "voice": "",
      "vid": "",
      "value": "",
      "said": ""
    },
    {
      "function": "XENDIF",
      "argument": [
        "0"
      ],
      "name": "",
      "msgidx": -1,
      "voice": "",
      "vid": "",
      "value": "",
      "said": ""
    },
    {
      "function": "XFADE",
      "argument": [
        "XFTS,MaskTexture.None,0",
        "XFOT,0.5"
      ],
      "name": "",
      "msgidx": -1,
      "voice": "",
      "vid": "",
      "value": "",
      "said": ""
    },
    {
      "function": "XWXB",
      "argument": [],
      "name": "",
      "msgidx": -1,
      "voice": "",
      "vid": "",
      "value": "",
      "said": ""
    },
    {
      "function": "SNSE",
      "argument": [
        "NSE_OFF",
        "0"
      ],
      "name": "",
      "msgidx": -1,
      "voice": "",
      "vid": "",
      "value": "",
      "said": ""
    },
    {
      "function": "XWXB",
      "argument": [],
      "name": "",
      "msgidx": -1,
      "voice": "",
      "vid": "",
      "value": "",
      "said": ""
    },
    {
      "function": "XLCYDRAW",
      "argument": [
        "XLCYLOAD,Lucy.Type.BACK,BG_189_A0",
        "XLCYFADE,0,0.001"
      ],
      "name": "",
      "msgidx": -1,
      "voice": "",
      "vid": "",
      "value": "",
      "said": ""
    },
    {
      "function": "XLCYDRAW",
      "argument": [
        "XLCYINIT",
        "XLCYFIND,FindType.SP_C",
        "XLCYLOAD,Lucy.Type.BUST,BU_OFF",
        "XLCYLOAD,Lucy.Type.SP_L,SP_OFF",
        "XLCYLOAD,Lucy.Type.SP_R,SP_OFF",
        "XLCYLOAD,Lucy.Type.SP_C,SP_OFF",
        "XLCYLOAD,Lucy.Type.MG_0,MG_OFF",
        "XLCYLOAD,Lucy.Type.MG_1,MG_OFF",
        "XLCYFADE,0,0.25"
      ],
      "name": "",
      "msgidx": -1,
      "voice": "",
      "vid": "",
      "value": "",
      "said": ""
    },
    {
      "function": "SBGM",
      "argument": [
        "BGM_SAME"
      ],
      "name": "",
      "msgidx": -1,
      "voice": "",
      "vid": "",
      "value": "",
      "said": ""
    },
    {
      "function": "SESE",
      "argument": [
        "ESE_OFF",
        "0"
      ],
      "name": "",
      "msgidx": -1,
      "voice": "",
      "vid": "",
      "value": "",
      "said": ""
    },
    {
      "function": "XMON",
      "argument": [],
      "name": "",
      "msgidx": -1,
      "voice": "",
      "vid": "",
      "value": "",
      "said": ""
    },
    {
      "function": "XFADE",
      "argument": [
        "XFTS,MaskTexture.None,0",
        "XFIN,0.5"
      ],
      "name": "",
      "msgidx": -1,
      "voice": "",
      "vid": "",
      "value": "",
      "said": ""
    },
    {
      "function": "XMESS",
      "argument": [
        "(Although I had a lot of trouble ...)"
      ],
      "name": "Rin（thinking）",
      "msgidx": 29,
      "voice": "",
      "vid": "",
      "value": "",
      "said": ""
    },
    {
      "function": "XWCR",
      "argument": [],
      "name": "",
      "msgidx": -1,
      "voice": "",
      "vid": "",
      "value": "",
      "said": ""
    },
    {
      "function": "XMESS",
      "argument": [
        "(I managed to run all the way)"
      ],
      "name": "Rin（thinking）",
      "msgidx": 30,
      "voice": "",
      "vid": "",
      "value": "",
      "said": ""
    },
    {
      "function": "XWCR",
      "argument": [],
      "name": "",
      "msgidx": -1,
      "voice": "",
      "vid": "",
      "value": "",
      "said": ""
    },
    {
      "function": "SBGM",
      "argument": [
        "BGM_OFF"
      ],
      "name": "",
      "msgidx": -1,
      "voice": "",
      "vid": "",
      "value": "",
      "said": ""
    },
    {
      "function": "XPLACEENTRY",
      "argument": [
        "3"
      ],
      "name": "",
      "msgidx": -1,
      "voice": "",
      "vid": "",
      "value": "",
      "said": ""
    },
    {
      "function": "GON",
      "argument": [
        "SCR_L_YC_ARRV_A3_ALLEND"
      ],
      "name": "",
      "msgidx": -1,
      "voice": "",
      "vid": "",
      "value": "",
      "said": ""
    },
    {
      "function": "XCLR",
      "argument": [],
      "name": "",
      "msgidx": -1,
      "voice": "",
      "vid": "",
      "value": "",
      "said": ""
    },
    {
      "function": "XFADE",
      "argument": [
        "XFED,0.5"
      ],
      "name": "",
      "msgidx": -1,
      "voice": "",
      "vid": "",
      "value": "",
      "said": ""
    },
    {
      "function": "XCLR",
      "argument": [],
      "name": "",
      "msgidx": -1,
      "voice": "",
      "vid": "",
      "value": "",
      "said": ""
    },
    {
      "function": "XEOS",
      "argument": [],
      "name": "",
      "msgidx": -1,
      "voice": "",
      "vid": "",
      "value": "",
      "said": ""
    }
  ]
}
